{
  "indexes": [
    {
      "collectionGroup": "teams",
      "queryScope": "COLLECTION",
      "fields": [
        {
          "fieldPath": "status",
          "order": "ASCENDING"
        },
        {
          "fieldPath": "tokenBalance",
          "order": "DESCENDING"
        }
      ]
    },
    {
      "collectionGroup": "teams",
      "queryScope": "COLLECTION",
      "fields": [
        {
          "fieldPath": "status",
          "order": "ASCENDING"
        },
        {
          "fieldPath": "cumulativeResponseTimeMs",
          "order": "ASCENDING"
        }
      ]
    },
    {
      "collectionGroup": "responses",
      "queryScope": "COLLECTION",
      "fields": [
        {
          "fieldPath": "teamId",
          "order": "ASCENDING"
        },
        {
          "fieldPath": "questionIndex",
          "order": "ASCENDING"
        }
      ]
    },
    {
      "collectionGroup": "questions",
      "queryScope": "COLLECTION",
      "fields": [
        {
          "fieldPath": "index",
          "order": "ASCENDING"
        }
      ]
    }
  ],
  "fieldOverrides": []
}
